pyfiniium/__init__.py
pyfiniium/_version.py
pyfiniium/composite.py
pyfiniium/infiniium.py
pyfiniium/pyfiniium.py
pyfiniium-0.0.4.dist-info/LICENSE
pyfiniium-0.0.4.dist-info/METADATA
pyfiniium-0.0.4.dist-info/WHEEL
pyfiniium-0.0.4.dist-info/top_level.txt
pyfiniium-0.0.4.dist-info/RECORD
